TijaToolsProgressRing/__init__.py
TijaToolsProgressRing/progress_ring.py
TijaToolsProgressRing/tijatools_terminal_progress_ring_tests.py
tijatools/__init__.py
tijatools/progress_ring.py
tijatools/tijatools_terminal_progress_ring_tests.py
tijatools-0.1.2.dist-info/LICENSE
tijatools-0.1.2.dist-info/METADATA
tijatools-0.1.2.dist-info/WHEEL
tijatools-0.1.2.dist-info/top_level.txt
tijatools-0.1.2.dist-info/RECORD
