Metadata-Version: 2.1
Name: tijatools
Version: 0.1.2
Summary: A customizable progress ring for terminal applications.
Author: Janos Tigyi
Author-email: tigyi.janos@bugfactory.hu
Classifier: Programming Language :: Python :: 3
Classifier: License :: OSI Approved :: MIT License
Classifier: Operating System :: OS Independent
Requires-Python: >=3.6
License-File: LICENSE
Requires-Dist: asyncio
